meowiz/__init__.py
meowiz/__main__.py
meowiz-0.1.0.dist-info/METADATA
meowiz-0.1.0.dist-info/WHEEL
meowiz-0.1.0.dist-info/entry_points.txt
meowiz-0.1.0.dist-info/RECORD
