Metadata-Version: 2.1
Name: meowiz
Version: 0.1.0
Summary: 
Author: karl robeck alferez
Author-email: karlalferezfx@gmail.com
Requires-Python: >=3.12,<4.0
Classifier: Programming Language :: Python :: 3
Classifier: Programming Language :: Python :: 3.12
Requires-Dist: jinja2 (>=3.1.3,<4.0.0)
Requires-Dist: typer[all] (>=0.9.0,<0.10.0)
Requires-Dist: watchfiles (>=0.21.0,<0.22.0)
